MLData-2.0.0.data/data/ReleaseNotes.md
MLData-2.0.0.dist-info/DESCRIPTION.rst
MLData-2.0.0.dist-info/METADATA
MLData-2.0.0.dist-info/RECORD
MLData-2.0.0.dist-info/WHEEL
MLData-2.0.0.dist-info/metadata.json
MLData-2.0.0.dist-info/top_level.txt
mldata/__init__.py
mldata/main.py
mldata/lib/__init__.py
mldata/lib/category_converter.py
mldata/lib/cleaner.py
mldata/lib/helper.py
mldata/lib/normalizer.py
mldata/lib/processor.py
mldata/tests/__init__.py
mldata/tests/test_category_converter.py
mldata/tests/test_clearner.py
mldata/tests/test_helper.py
mldata/tests/test_normalizer.py
mldata/tests/test_processor.py
mldata/tests/outputs/__init__.py
