Metadata-Version: 2.0
Name: MLData
Version: 2.0.0
Summary: MLData is used to clean data before machine learning process!
Home-page: https://github.com/wuhaifengdhu/MLData.git
Author: Wu Haifeng
Author-email: wuhaifengdhu@163.com
License: UNKNOWN
Platform: UNKNOWN
Requires-Dist: six (>=1.11.0)
